pyversions/__init__.py
pyversions/pyversions.py
pyversions-0.0.3.dist-info/LICENSE
pyversions-0.0.3.dist-info/METADATA
pyversions-0.0.3.dist-info/WHEEL
pyversions-0.0.3.dist-info/top_level.txt
pyversions-0.0.3.dist-info/RECORD
