Metadata-Version: 2.1
Name: pyversions
Version: 0.0.3
Summary: Get versions of all imported modules in current session
Home-page: https://github.com/demotu/pyversions
Author: Marcos Duarte
Author-email: duartexyz@gmail.com
License: UNKNOWN
Platform: UNKNOWN
Classifier: Programming Language :: Python :: 3
Classifier: License :: OSI Approved :: MIT License
Classifier: Operating System :: OS Independent
Requires-Python: >=3.6
